README.md
setup.py
kmy_scrap/__init__.py
kmy_scrap/kmy_scrap.py
kmy_web_scraping.egg-info/PKG-INFO
kmy_web_scraping.egg-info/SOURCES.txt
kmy_web_scraping.egg-info/dependency_links.txt
kmy_web_scraping.egg-info/requires.txt
kmy_web_scraping.egg-info/top_level.txt