Metadata-Version: 2.1
Name: kmy-web-scraping
Version: 0.1.0
Summary: search engines use scraping!
Home-page: https://github.com/ExsoKamabay/Api-scrap
Author: Exso Kamabay
License: Apache License 2.0
Keywords: kamabay,technology,search,information,enggine
Classifier: License :: OSI Approved :: Apache Software License
Classifier: Operating System :: OS Independent
Classifier: Programming Language :: Python :: 3
Classifier: Topic :: Utilities
Requires-Dist: requests==2.31.0
Requires-Dist: bs4==0.0.1
Requires-Dist: youtube-search==2.1.2
